{
"type": "FeatureCollection",
"crs": { "type": "name", "properties": { "name": "urn:ogc:def:crs:OGC:1.3:CRS84" } },
"features": [
	{ "type": "Feature", "properties": { "osm_id": "1685191610", "name": "Wharfedale Deli", "other_tags": "\"shop\"=>\"deli\",\"fhrs:id\"=>\"327648\",\"addr:city\"=>\"Ilkley\",\"addr:street\"=>\"Main Street\",\"source:addr\"=>\"FHRS Open Data\",\"addr:district\"=>\"Burley In Wharfedale\",\"addr:postcode\"=>\"LS29 7JN\",\"addr:housenumber\"=>\"107a\"" }, "geometry": { "type": "Point", "coordinates": [ -1.7504445, 53.9137818 ] } },
	{ "type": "Feature", "properties": { "osm_id": "6836925889", "name": "Friends of Ham", "other_tags": "\"addr:city\"=>\"Ilkley\",\"addr:housenumber\"=>\"6\",\"addr:street\"=>\"Wells Road\",\"fhrs:id\"=>\"801543\",\"shop\"=>\"deli\",\"source:addr\"=>\"FHRS Open Data\"" }, "geometry": { "type": "Point", "coordinates": [ -1.8228572, 53.9241718 ] } }
]
}
