{
"type": "FeatureCollection",
"crs": { "type": "name", "properties": { "name": "urn:ogc:def:crs:OGC:1.3:CRS84" } },
"features": [
	{ "type": "Feature", "properties": { "osm_id": "6379620614", "name": "Funzy", "other_tags": "\"fee\"=>\"yes\",\"indoor\"=>\"yes\",\"indoor_play\"=>\"inflatable\",\"leisure\"=>\"indoor_play\",\"level\"=>\"0\",\"phone\"=>\"+44 1274 307130\",\"strapline\"=>\"Inflatable theme park\",\"website\"=>\"https:\/\/funzy.co.uk\/\"" }, "geometry": { "type": "Point", "coordinates": [ -1.7474498, 53.7920907 ] } }
]
}
