{
"type": "FeatureCollection",
"crs": { "type": "name", "properties": { "name": "urn:ogc:def:crs:OGC:1.3:CRS84" } },
"features": [
	{ "type": "Feature", "properties": { "osm_id": "2195805654", "name": "Argos", "other_tags": "\"addr:city\"=>\"Bradford\",\"addr:housename\"=>\"Unit 15 Forster Square Retail\",\"addr:housenumber\"=>\"53\",\"addr:postcode\"=>\"BD1 4RN\",\"addr:street\"=>\"Valley Road\",\"brand\"=>\"Argos\",\"brand:wikidata\"=>\"Q4789707\",\"brand:wikipedia\"=>\"en:Argos (retailer)\",\"contact:website\"=>\"https:\/\/www.argos.co.uk\/stores\/545-bradford-forster-square-argos\",\"designation\"=>\"Catalogue Shop\",\"fhrs:id\"=>\"325051\",\"shop\"=>\"catalogue\",\"source:addr\"=>\"FHRS Open Data\"" }, "geometry": { "type": "Point", "coordinates": [ -1.7552013, 53.801301 ] } },
	{ "type": "Feature", "properties": { "osm_id": "2358646362", "name": "Argos", "other_tags": "\"brand\"=>\"Argos\",\"brand:wikidata\"=>\"Q4789707\",\"brand:wikipedia\"=>\"en:Argos (retailer)\",\"shop\"=>\"catalogue\"" }, "geometry": { "type": "Point", "coordinates": [ -1.776194, 53.8338057 ] } }
]
}
