{
"type": "FeatureCollection",
"crs": { "type": "name", "properties": { "name": "urn:ogc:def:crs:OGC:1.3:CRS84" } },
"features": [
	{ "type": "Feature", "properties": { "osm_id": "8780090929", "name": "earnestly obi jewellery", "other_tags": "\"addr:city\"=>\"Bradford\",\"addr:housenumber\"=>\"1\",\"addr:postcode\"=>\"BD10 8DB\",\"addr:street\"=>\"Farm Hill Road\",\"shop\"=>\"outpost\",\"website\"=>\"earnestlyobijewellery.co.uk\"" }, "geometry": { "type": "Point", "coordinates": [ -1.7298977, 53.8264502 ] } }
]
}
