{
"type": "FeatureCollection",
"crs": { "type": "name", "properties": { "name": "urn:ogc:def:crs:OGC:1.3:CRS84" } },
"features": [
	{ "type": "Feature", "properties": { "osm_id": "1685191610", "name": "Wharfedale Deli", "other_tags": "\"addr:city\"=>\"Ilkley\",\"addr:district\"=>\"Burley In Wharfedale\",\"addr:housenumber\"=>\"107a\",\"addr:postcode\"=>\"LS29 7JN\",\"addr:street\"=>\"Main Street\",\"fhrs:id\"=>\"327648\",\"shop\"=>\"deli\",\"source:addr\"=>\"FHRS Open Data\"" }, "geometry": { "type": "Point", "coordinates": [ -1.7504445, 53.9137818 ] } }
]
}
