{
"type": "FeatureCollection",
"crs": { "type": "name", "properties": { "name": "urn:ogc:def:crs:OGC:1.3:CRS84" } },
"features": [
	{ "type": "Feature", "properties": { "osm_id": "2358646362", "name": "Argos", "other_tags": "\"shop\"=>\"catalogue\",\"brand\"=>\"Argos\",\"brand:wikidata\"=>\"Q4789707\",\"brand:wikipedia\"=>\"en:Argos (retailer)\"" }, "geometry": { "type": "Point", "coordinates": [ -1.776194, 53.8338057 ] } }
]
}
