{
"type": "FeatureCollection",
"crs": { "type": "name", "properties": { "name": "urn:ogc:def:crs:OGC:1.3:CRS84" } },
"features": [
	{ "type": "Feature", "properties": { "osm_id": "8905747322", "name": "Bradford Ice Arena", "other_tags": "\"leisure\"=>\"ice_rink\"" }, "geometry": { "type": "Point", "coordinates": [ -1.7569704, 53.7903437 ] } }
]
}
