{
"type": "FeatureCollection",
"crs": { "type": "name", "properties": { "name": "urn:ogc:def:crs:OGC:1.3:CRS84" } },
"features": [
	{ "type": "Feature", "properties": { "osm_id": "5643784151", "name": "Wilko", "other_tags": "\"shop\"=>\"homewares\",\"website\"=>\"https:\/\/www.wilko.com\/\",\"opening_hours\"=>\"Mo-Sa 08:30-17:30; Su 10:00-16:00\"" }, "geometry": { "type": "Point", "coordinates": [ -1.7777366, 53.8340581 ] } }
]
}
