{
"type": "FeatureCollection",
"crs": { "type": "name", "properties": { "name": "urn:ogc:def:crs:OGC:1.3:CRS84" } },
"features": [
	{ "type": "Feature", "properties": { "osm_id": "4489272589", "name": "The Rhyddings", "amenity": "animal_boarding", "other_tags": "\"addr:city\"=>\"Ilkley\",\"addr:street\"=>\"Bradford Road\",\"addr:suburb\"=>\"Burley in Wharfedale\",\"addr:postcode\"=>\"LS29 7QP\",\"contact:email\"=>\"jompeel@btinternet.com\",\"contact:phone\"=>\"+44 1943 872802\",\"animal_boarding\"=>\"dog;cat\"" }, "geometry": { "type": "Point", "coordinates": [ -1.7409847, 53.9001754 ] } }
]
}
