{
"type": "FeatureCollection",
"crs": { "type": "name", "properties": { "name": "urn:ogc:def:crs:OGC:1.3:CRS84" } },
"features": [
	{ "type": "Feature", "properties": { "osm_id": "8633753058", "name": "Keighley Cartridges", "other_tags": "\"shop\"=>\"printer_ink\"" }, "geometry": { "type": "Point", "coordinates": [ -1.9047198, 53.8678856 ] } }
]
}
