{
"type": "FeatureCollection",
"crs": { "type": "name", "properties": { "name": "urn:ogc:def:crs:OGC:1.3:CRS84" } },
"features": [
	{ "type": "Feature", "properties": { "osm_id": "5643784332", "name": "Shipley Phones", "other_tags": "\"shop\"=>\"mobile_phone\",\"phone\"=>\"+44 1274599055\",\"website\"=>\"http:\/\/www.shipleyphones.co.uk\/\",\"addr:city\"=>\"Shipley\",\"addr:postcode\"=>\"BD18 3QW\",\"opening_hours\"=>\"Mo-Sa 09:00-17:30\"" }, "geometry": { "type": "Point", "coordinates": [ -1.7780213, 53.8340368 ] } },
	{ "type": "Feature", "properties": { "osm_id": "8047164099", "name": "O2", "other_tags": "\"brand\"=>\"O2\",\"brand:wikidata\"=>\"Q1759255\",\"brand:wikipedia\"=>\"en:Telefónica Europe\",\"shop\"=>\"mobile_phone\"" }, "geometry": { "type": "Point", "coordinates": [ -1.7537107, 53.800994 ] } }
]
}
