{
"type": "FeatureCollection",
"crs": { "type": "name", "properties": { "name": "urn:ogc:def:crs:OGC:1.3:CRS84" } },
"features": [
	{ "type": "Feature", "properties": { "osm_id": "2358555952", "name": "Elsie Russell", "other_tags": "\"shop\"=>\"florist\"" }, "geometry": { "type": "Point", "coordinates": [ -1.7786483, 53.8345732 ] } },
	{ "type": "Feature", "properties": { "osm_id": "3497988098", "name": "Mrs Bouquet", "other_tags": "\"shop\"=>\"florist\"" }, "geometry": { "type": "Point", "coordinates": [ -1.7090229, 53.7674583 ] } }
]
}
