{
"type": "FeatureCollection",
"crs": { "type": "name", "properties": { "name": "urn:ogc:def:crs:OGC:1.3:CRS84" } },
"features": [
	{ "type": "Feature", "properties": { "osm_id": "382568580", "name": "SS Motor Tech", "other_tags": "\"shop\"=>\"car_parts\",\"building\"=>\"retail\"" }, "geometry": { "type": "Point", "coordinates": [ -1.7761241, 53.8072349 ] } },
	{ "type": "Feature", "properties": { "osm_id": "2661206209", "name": "Motor World", "other_tags": "\"shop\"=>\"car_parts\"" }, "geometry": { "type": "Point", "coordinates": [ -1.8214444, 53.926164 ] } }
]
}
