{
"type": "FeatureCollection",
"crs": { "type": "name", "properties": { "name": "urn:ogc:def:crs:OGC:1.3:CRS84" } },
"features": [
	{ "type": "Feature", "properties": { "osm_id": "9130019937", "name": "Alpman Home Textiles", "other_tags": "\"shop\"=>\"curtain\"" }, "geometry": { "type": "Point", "coordinates": [ -1.7770051, 53.8327847 ] } }
]
}
