{
"type": "FeatureCollection",
"crs": { "type": "name", "properties": { "name": "urn:ogc:def:crs:OGC:1.3:CRS84" } },
"features": [
	{ "type": "Feature", "properties": { "osm_id": "1885259751", "name": "Virgin Active", "other_tags": "\"sport\"=>\"swimming\",\"covered\"=>\"yes\",\"leisure\"=>\"swimming_pool\"" }, "geometry": { "type": "Point", "coordinates": [ -1.5461011, 53.8001647 ] } }
]
}
