{
"type": "FeatureCollection",
"crs": { "type": "name", "properties": { "name": "urn:ogc:def:crs:OGC:1.3:CRS84" } },
"features": [
	{ "type": "Feature", "properties": { "osm_id": "1284137234", "amenity": "grit_bin" }, "geometry": { "type": "Point", "coordinates": [ -1.5234864, 53.807803 ] } },
	{ "type": "Feature", "properties": { "osm_id": "1428145476", "amenity": "grit_bin" }, "geometry": { "type": "Point", "coordinates": [ -1.5431043, 53.8446972 ] } },
	{ "type": "Feature", "properties": { "osm_id": "1428147709", "amenity": "grit_bin" }, "geometry": { "type": "Point", "coordinates": [ -1.5461232, 53.8449032 ] } },
	{ "type": "Feature", "properties": { "osm_id": "1428147710", "amenity": "grit_bin" }, "geometry": { "type": "Point", "coordinates": [ -1.5433165, 53.8454565 ] } },
	{ "type": "Feature", "properties": { "osm_id": "1428147711", "amenity": "grit_bin" }, "geometry": { "type": "Point", "coordinates": [ -1.5430161, 53.8464232 ] } },
	{ "type": "Feature", "properties": { "osm_id": "2235472524", "amenity": "grit_bin" }, "geometry": { "type": "Point", "coordinates": [ -1.574416, 53.760724 ] } },
	{ "type": "Feature", "properties": { "osm_id": "2242699408", "amenity": "grit_bin" }, "geometry": { "type": "Point", "coordinates": [ -1.6981325, 53.9143909 ] } },
	{ "type": "Feature", "properties": { "osm_id": "2354930875", "amenity": "grit_bin" }, "geometry": { "type": "Point", "coordinates": [ -1.6991781, 53.9151976 ] } },
	{ "type": "Feature", "properties": { "osm_id": "2406928418", "amenity": "grit_bin" }, "geometry": { "type": "Point", "coordinates": [ -1.7000653, 53.9144513 ] } },
	{ "type": "Feature", "properties": { "osm_id": "3942727568", "amenity": "grit_bin" }, "geometry": { "type": "Point", "coordinates": [ -1.6943242, 53.9037514 ] } },
	{ "type": "Feature", "properties": { "osm_id": "5506378734", "amenity": "grit_bin" }, "geometry": { "type": "Point", "coordinates": [ -1.531489, 53.7981003 ] } },
	{ "type": "Feature", "properties": { "osm_id": "7895251923", "amenity": "grit_bin" }, "geometry": { "type": "Point", "coordinates": [ -1.6272238, 53.8254851 ] } },
	{ "type": "Feature", "properties": { "osm_id": "7989634822", "amenity": "grit_bin" }, "geometry": { "type": "Point", "coordinates": [ -1.7150029, 53.8760883 ] } },
	{ "type": "Feature", "properties": { "osm_id": "7989634830", "amenity": "grit_bin" }, "geometry": { "type": "Point", "coordinates": [ -1.7151662, 53.8759717 ] } },
	{ "type": "Feature", "properties": { "osm_id": "7989634855", "amenity": "grit_bin" }, "geometry": { "type": "Point", "coordinates": [ -1.7149612, 53.8757229 ] } },
	{ "type": "Feature", "properties": { "osm_id": "8303600938", "amenity": "grit_bin" }, "geometry": { "type": "Point", "coordinates": [ -1.6395414, 53.8358542 ] } },
	{ "type": "Feature", "properties": { "osm_id": "8354707800", "amenity": "grit_bin" }, "geometry": { "type": "Point", "coordinates": [ -1.6400195, 53.8292372 ] } },
	{ "type": "Feature", "properties": { "osm_id": "8656153397", "amenity": "grit_bin" }, "geometry": { "type": "Point", "coordinates": [ -1.7129522, 53.8747171 ] } },
	{ "type": "Feature", "properties": { "osm_id": "8656153398", "amenity": "grit_bin" }, "geometry": { "type": "Point", "coordinates": [ -1.7150935, 53.875507 ] } },
	{ "type": "Feature", "properties": { "osm_id": "8656153400", "amenity": "grit_bin" }, "geometry": { "type": "Point", "coordinates": [ -1.7178213, 53.8785211 ] } },
	{ "type": "Feature", "properties": { "osm_id": "8656153401", "amenity": "grit_bin" }, "geometry": { "type": "Point", "coordinates": [ -1.7181598, 53.8788382 ] } },
	{ "type": "Feature", "properties": { "osm_id": "8656153402", "amenity": "grit_bin" }, "geometry": { "type": "Point", "coordinates": [ -1.7168782, 53.8793576 ] } }
]
}
