{
"type": "FeatureCollection",
"crs": { "type": "name", "properties": { "name": "urn:ogc:def:crs:OGC:1.3:CRS84" } },
"features": [
	{ "type": "Feature", "properties": { "osm_id": "7141864954", "name": "EYG Solar", "other_tags": "\"shop\"=>\"glaziery\"" }, "geometry": { "type": "Point", "coordinates": [ -1.4700513, 53.7961725 ] } }
]
}
