{
"type": "FeatureCollection",
"crs": { "type": "name", "properties": { "name": "urn:ogc:def:crs:OGC:1.3:CRS84" } },
"features": [
	{ "type": "Feature", "properties": { "osm_id": "518142655", "name": "Hunters Greave Activity Centre", "amenity": "activity_centre", "other_tags": "\"club\"=>\"scout\",\"building\"=>\"yes\"" }, "geometry": { "type": "Point", "coordinates": [ -1.6307131, 53.8255912 ] } }
]
}
