{
"type": "FeatureCollection",
"crs": { "type": "name", "properties": { "name": "urn:ogc:def:crs:OGC:1.3:CRS84" } },
"features": [
	{ "type": "Feature", "properties": { "osm_id": "4885695946", "name": "Yorkshire Linen Company", "other_tags": "\"shop\"=>\"houseware\"" }, "geometry": { "type": "Point", "coordinates": [ -1.5442251, 53.8011399 ] } },
	{ "type": "Feature", "properties": { "osm_id": "5941346414", "name": "Le Creuset", "other_tags": "\"shop\"=>\"houseware\",\"brand\"=>\"Le Creuset\",\"addr:city\"=>\"Leeds\",\"addr:street\"=>\"Queen Victoria Street\",\"addr:postcode\"=>\"LS1 6BE\",\"brand:wikidata\"=>\"Q555861\",\"brand:wikipedia\"=>\"en:Le Creuset\",\"addr:housenumber\"=>\"36\"" }, "geometry": { "type": "Point", "coordinates": [ -1.5405361, 53.7981899 ] } },
	{ "type": "Feature", "properties": { "osm_id": "6001482117", "name": "Home Star", "other_tags": "\"shop\"=>\"houseware\"" }, "geometry": { "type": "Point", "coordinates": [ -1.5381973, 53.7972551 ] } },
	{ "type": "Feature", "properties": { "osm_id": "6046838149", "name": "Touchwood", "other_tags": "\"shop\"=>\"houseware\",\"fhrs:id\"=>\"687524\",\"addr:town\"=>\"Wetherby\",\"addr:street\"=>\"High Street\",\"addr:postcode\"=>\"LS22 6LT\",\"addr:housenumber\"=>\"20a\"" }, "geometry": { "type": "Point", "coordinates": [ -1.3855353, 53.9277231 ] } }
]
}
