{
"type": "FeatureCollection",
"crs": { "type": "name", "properties": { "name": "urn:ogc:def:crs:OGC:1.3:CRS84" } },
"features": [
	{ "type": "Feature", "properties": { "osm_id": "1689398129", "amenity": "events_venue" }, "geometry": { "type": "Point", "coordinates": [ -1.4563297, 53.785166 ] } },
	{ "type": "Feature", "properties": { "osm_id": "2477751822", "name": "Tuesday Club", "amenity": "events_venue", "other_tags": "\"fhrs:id\"=>\"320360\",\"addr:city\"=>\"Leeds\",\"addr:street\"=>\"York Road\",\"addr:postcode\"=>\"LS9 9NT\",\"addr:housename\"=>\"The Irish Centre\"" }, "geometry": { "type": "Point", "coordinates": [ -1.5161317, 53.7972355 ] } },
	{ "type": "Feature", "properties": { "osm_id": "6769233571", "name": "Studio 24", "amenity": "events_venue", "other_tags": "\"addr:city\"=>\"Leeds\",\"addr:unit\"=>\"23a\",\"addr:street\"=>\"Mabgate\",\"addr:suburb\"=>\"Sheepscar\",\"addr:postcode\"=>\"LS9 7DZ\",\"addr:housenumber\"=>\"64-74\"" }, "geometry": { "type": "Point", "coordinates": [ -1.5308735, 53.801766 ] } }
]
}
