{
"type": "FeatureCollection",
"crs": { "type": "name", "properties": { "name": "urn:ogc:def:crs:OGC:1.3:CRS84" } },
"features": [
	{ "type": "Feature", "properties": { "osm_id": "292238581", "other_tags": "\"shop\"=>\"erotic\"" }, "geometry": { "type": "Point", "coordinates": [ -1.5501768, 53.7707916 ] } },
	{ "type": "Feature", "properties": { "osm_id": "313197511", "name": "Pulse and Cocktails", "other_tags": "\"shop\"=>\"erotic\"" }, "geometry": { "type": "Point", "coordinates": [ -1.5685682, 53.7956908 ] } },
	{ "type": "Feature", "properties": { "osm_id": "333452847", "name": "Nice 'n' Naughty", "other_tags": "\"old_name\"=>\"Clone Zone\",\"shop\"=>\"erotic\"" }, "geometry": { "type": "Point", "coordinates": [ -1.5423616, 53.7952566 ] } },
	{ "type": "Feature", "properties": { "osm_id": "357751953", "name": "Simply Pleasure", "other_tags": "\"addr:city\"=>\"Leeds\",\"addr:housenumber\"=>\"5\",\"addr:postcode\"=>\"LS1 4AF\",\"addr:street\"=>\"Briggate\",\"shop\"=>\"erotic\"" }, "geometry": { "type": "Point", "coordinates": [ -1.5425725, 53.7947461 ] } }
]
}
