{
"type": "FeatureCollection",
"crs": { "type": "name", "properties": { "name": "urn:ogc:def:crs:OGC:1.3:CRS84" } },
"features": [
	{ "type": "Feature", "properties": { "osm_id": "10024170491", "amenity": "waste_disposal", "other_tags": "\"access\"=>\"private\",\"collection_times\"=>\"Thu\"" }, "geometry": { "type": "Point", "coordinates": [ -1.4245292, 53.8028743 ] } }
]
}
