{
"type": "FeatureCollection",
"crs": { "type": "name", "properties": { "name": "urn:ogc:def:crs:OGC:1.3:CRS84" } },
"features": [
	{ "type": "Feature", "properties": { "osm_id": "317087702", "name": "Morlands", "other_tags": "\"shop\"=>\"bathroom_furnishing\",\"website\"=>\"www.morlandbathrooms.com\",\"addr:city\"=>\"Leeds\",\"addr:street\"=>\"High Court Lane\",\"addr:housenumber\"=>\"21\"" }, "geometry": { "type": "Point", "coordinates": [ -1.5372441, 53.7949482 ] } },
	{ "type": "Feature", "properties": { "osm_id": "4999354651", "name": "Soak", "other_tags": "\"shop\"=>\"bathroom_furnishing\"" }, "geometry": { "type": "Point", "coordinates": [ -1.4478678, 53.7516407 ] } }
]
}
