{
"type": "FeatureCollection",
"crs": { "type": "name", "properties": { "name": "urn:ogc:def:crs:OGC:1.3:CRS84" } },
"features": [
	{ "type": "Feature", "properties": { "osm_id": "7448481139", "name": "Hainswoofs", "other_tags": "\"shop\"=>\"pet_grooming\"" }, "geometry": { "type": "Point", "coordinates": [ -1.6984223, 53.7921364 ] } },
	{ "type": "Feature", "properties": { "osm_id": "7869213669", "name": "Shampooch Parlour", "other_tags": "\"shop\"=>\"pet_grooming\"" }, "geometry": { "type": "Point", "coordinates": [ -1.4523909, 53.8043019 ] } }
]
}
