{
"type": "FeatureCollection",
"crs": { "type": "name", "properties": { "name": "urn:ogc:def:crs:OGC:1.3:CRS84" } },
"features": [
	{ "type": "Feature", "properties": { "osm_id": "4375827190", "name": "Base", "other_tags": "\"phone\"=>\"+44 113 242 7730\",\"leisure\"=>\"sauna\",\"website\"=>\"http:\/\/www.base-leeds.com\/#random\",\"addr:street\"=>\"Heaton's Court\",\"addr:postcode\"=>\"LS1 4LJ\",\"addr:housenumber\"=>\"7\"" }, "geometry": { "type": "Point", "coordinates": [ -1.5437251, 53.7949211 ] } }
]
}
