{
"type": "FeatureCollection",
"crs": { "type": "name", "properties": { "name": "urn:ogc:def:crs:OGC:1.3:CRS84" } },
"features": [
	{ "type": "Feature", "properties": { "osm_id": "333799044", "name": "Change Group", "amenity": "bureau_de_change" }, "geometry": { "type": "Point", "coordinates": [ -1.5437994, 53.7991737 ] } },
	{ "type": "Feature", "properties": { "osm_id": "2888250701", "name": "Sainsburys Currency Exchange", "amenity": "bureau_de_change", "other_tags": "\"operator\"=>\"Sainsburys\"" }, "geometry": { "type": "Point", "coordinates": [ -1.435161, 53.794207 ] } },
	{ "type": "Feature", "properties": { "osm_id": "4465596498", "amenity": "bureau_de_change" }, "geometry": { "type": "Point", "coordinates": [ -1.4766782, 53.8061799 ] } },
	{ "type": "Feature", "properties": { "osm_id": "4475950133", "name": "No1 Currency", "amenity": "bureau_de_change" }, "geometry": { "type": "Point", "coordinates": [ -1.4501291, 53.8070137 ] } }
]
}
