{
"type": "FeatureCollection",
"crs": { "type": "name", "properties": { "name": "urn:ogc:def:crs:OGC:1.3:CRS84" } },
"features": [
	{ "type": "Feature", "properties": { "osm_id": "7798963003", "name": "Otley Boats", "amenity": "boat_rental", "other_tags": "\"contact:facebook\"=>\"https:\/\/www.facebook.com\/OtleyBoats\",\"description\"=>\"rental rowing and paddle boats\"" }, "geometry": { "type": "Point", "coordinates": [ -1.6945688, 53.9092767 ] } }
]
}
