{
"type": "FeatureCollection",
"crs": { "type": "name", "properties": { "name": "urn:ogc:def:crs:OGC:1.3:CRS84" } },
"features": [
	{ "type": "Feature", "properties": { "osm_id": "1351523108", "name": "Vantage Toyota Leeds", "other_tags": "\"brand\"=>\"Toyota\",\"shop\"=>\"car;car_repair\"" }, "geometry": { "type": "Point", "coordinates": [ -1.570048, 53.7870776 ] } }
]
}
