{
"type": "FeatureCollection",
"crs": { "type": "name", "properties": { "name": "urn:ogc:def:crs:OGC:1.3:CRS84" } },
"features": [
	{ "type": "Feature", "properties": { "osm_id": "4046566531", "amenity": "parcel_locker", "ref": "UKYEA11964", "other_tags": "\"brand\"=>\"InPost\",\"brand:wikidata\"=>\"Q3182097\",\"operator\"=>\"InPost\",\"parcel_mail_in\"=>\"yes\",\"parcel_pickup\"=>\"yes\"" }, "geometry": { "type": "Point", "coordinates": [ -1.6765749, 53.8602067 ] } },
	{ "type": "Feature", "properties": { "osm_id": "4306600681", "amenity": "parcel_locker", "other_tags": "\"brand\"=>\"InPost\",\"brand:wikidata\"=>\"Q3182097\",\"collection_times\"=>\"24\/7\",\"operator\"=>\"InPost\",\"parcel_mail_in\"=>\"yes\",\"parcel_pickup\"=>\"yes\"" }, "geometry": { "type": "Point", "coordinates": [ -1.6360604, 53.8039893 ] } },
	{ "type": "Feature", "properties": { "osm_id": "4846648973", "amenity": "parcel_locker", "ref": "UKMOR14987", "other_tags": "\"brand\"=>\"InPost\",\"brand:wikidata\"=>\"Q3182097\",\"operator\"=>\"InPost\",\"parcel_mail_in\"=>\"yes\",\"parcel_pickup\"=>\"yes\",\"vending\"=>\"parcel_pickup\"" }, "geometry": { "type": "Point", "coordinates": [ -1.6017482, 53.7522127 ] } },
	{ "type": "Feature", "properties": { "osm_id": "5218896692", "amenity": "parcel_locker", "ref": "UKLEE18826", "other_tags": "\"brand\"=>\"InPost\",\"brand:wikidata\"=>\"Q3182097\",\"operator\"=>\"InPost\",\"parcel_mail_in\"=>\"yes\",\"parcel_pickup\"=>\"yes\"" }, "geometry": { "type": "Point", "coordinates": [ -1.6028211, 53.7450532 ] } },
	{ "type": "Feature", "properties": { "osm_id": "6428424004", "name": "Amazon Locker - Noodle", "amenity": "parcel_locker", "other_tags": "\"brand\"=>\"Amazon Hub\",\"brand:en\"=>\"Amazon Hub Locker\",\"brand:ja\"=>\"Amazon Hub ロッカー\",\"brand:wikidata\"=>\"Q16974764\",\"brand:wikipedia\"=>\"en:Amazon Locker\",\"name:en\"=>\"Amazon Hub Locker\",\"name:ja\"=>\"Amazon Hub ロッカー\",\"operator\"=>\"Noodle\",\"parcel_mail_in\"=>\"yes\"" }, "geometry": { "type": "Point", "coordinates": [ -1.5360737, 53.7974157 ] } },
	{ "type": "Feature", "properties": { "osm_id": "7902885882", "amenity": "parcel_locker", "other_tags": "\"brand\"=>\"Locker InPost\",\"brand:wikidata\"=>\"Q3182097\",\"operator\"=>\"InPost\",\"parcel_mail_in\"=>\"yes\"" }, "geometry": { "type": "Point", "coordinates": [ -1.4300241, 53.7935917 ] } },
	{ "type": "Feature", "properties": { "osm_id": "9599191561", "amenity": "parcel_locker", "other_tags": "\"brand\"=>\"InPost\",\"colour\"=>\"white\",\"parcel_mail_in\"=>\"yes\",\"parcel_pickup\"=>\"yes\"" }, "geometry": { "type": "Point", "coordinates": [ -1.7108559, 53.8753419 ] } },
	{ "type": "Feature", "properties": { "osm_id": "10313490581", "amenity": "parcel_locker", "other_tags": "\"brand\"=>\"InPost\",\"brand:wikidata\"=>\"Q3182097\",\"operator\"=>\"InPost\",\"parcel_mail_in\"=>\"yes\",\"parcel_pickup\"=>\"yes\"" }, "geometry": { "type": "Point", "coordinates": [ -1.5845491, 53.8043254 ] } },
	{ "type": "Feature", "properties": { "osm_id": "10858976401", "amenity": "parcel_locker", "other_tags": "\"brand\"=>\"InPost\",\"opening_hours\"=>\"24\/7\"" }, "geometry": { "type": "Point", "coordinates": [ -1.640498, 53.8387581 ] } }
]
}
