{
"type": "FeatureCollection",
"crs": { "type": "name", "properties": { "name": "urn:ogc:def:crs:OGC:1.3:CRS84" } },
"features": [
	{ "type": "Feature", "properties": { "osm_id": "5777589643", "other_tags": "\"natural\"=>\"saddle\"" }, "geometry": { "type": "Point", "coordinates": [ -1.5466964, 53.7772393 ] } }
]
}
