{
"type": "FeatureCollection",
"crs": { "type": "name", "properties": { "name": "urn:ogc:def:crs:OGC:1.3:CRS84" } },
"features": [
	{ "type": "Feature", "properties": { "osm_id": "1162109886", "name": "The Curtain Shop", "other_tags": "\"shop\"=>\"upholstery\",\"phone\"=>\"+44 113 2587296\",\"addr:city\"=>\"Horsforth\",\"addr:street\"=>\"New Road Side\",\"addr:postcode\"=>\"LS18 4QB\",\"addr:housenumber\"=>\"102\"" }, "geometry": { "type": "Point", "coordinates": [ -1.6418221, 53.8322476 ] } }
]
}
