{
"type": "FeatureCollection",
"crs": { "type": "name", "properties": { "name": "urn:ogc:def:crs:OGC:1.3:CRS84" } },
"features": [
	{ "type": "Feature", "properties": { "osm_id": "1062426073", "other_tags": "\"brand\"=>\"Ford\",\"shop\"=>\"van\"" }, "geometry": { "type": "Point", "coordinates": [ -1.7732828, 53.6532484 ] } }
]
}
