{
"type": "FeatureCollection",
"crs": { "type": "name", "properties": { "name": "urn:ogc:def:crs:OGC:1.3:CRS84" } },
"features": [
	{ "type": "Feature", "properties": { "osm_id": "2128107759", "name": "Stitches", "other_tags": "\"shop\"=>\"tailor\"" }, "geometry": { "type": "Point", "coordinates": [ -1.5416342, 53.7989348 ] } },
	{ "type": "Feature", "properties": { "osm_id": "3718205540", "name": "Sew Quick", "other_tags": "\"addr:city\"=>\"Yeadon\",\"addr:housenumber\"=>\"35\",\"addr:postcode\"=>\"LS19 7SP\",\"addr:street\"=>\"High Street\",\"phone\"=>\"+44 113 250 4182\",\"shop\"=>\"tailor\"" }, "geometry": { "type": "Point", "coordinates": [ -1.6841065, 53.8662668 ] } },
	{ "type": "Feature", "properties": { "osm_id": "4411803755", "name": "Stitch Express", "other_tags": "\"shop\"=>\"tailor\",\"addr:street\"=>\"Westmorland Street\",\"addr:postcode\"=>\"WF1 1PJ\",\"addr:housenumber\"=>\"20\"" }, "geometry": { "type": "Point", "coordinates": [ -1.4965166, 53.6832276 ] } },
	{ "type": "Feature", "properties": { "osm_id": "4468401789", "name": "Hem and Stitch", "other_tags": "\"shop\"=>\"tailor\",\"addr:city\"=>\"Wakefield\",\"addr:street\"=>\"The Springs\",\"addr:postcode\"=>\"WF1 1PU\",\"addr:housenumber\"=>\"6\"" }, "geometry": { "type": "Point", "coordinates": [ -1.49529, 53.6830445 ] } }
]
}
