{
"type": "FeatureCollection",
"crs": { "type": "name", "properties": { "name": "urn:ogc:def:crs:OGC:1.3:CRS84" } },
"features": [
	{ "type": "Feature", "properties": { "osm_id": "3149866268", "name": "PJ Venner Sameday Courier Services", "amenity": "courier", "other_tags": "\"phone\"=>\"+44 7763 860028\"" }, "geometry": { "type": "Point", "coordinates": [ -1.6295799, 53.6938649 ] } }
]
}
