{
"type": "FeatureCollection",
"crs": { "type": "name", "properties": { "name": "urn:ogc:def:crs:OGC:1.3:CRS84" } },
"features": [
	{ "type": "Feature", "properties": { "osm_id": "443610055", "name": "W H Holdsworth", "other_tags": "\"shop\"=>\"amusement_arcade\",\"addr:city\"=>\"Otley\",\"is_in:town\"=>\"Otley\",\"addr:street\"=>\"Mercury Row\",\"addr:country\"=>\"GB\",\"addr:postcode\"=>\"LS21 3HE\",\"addr:housenumber\"=>\"7\"" }, "geometry": { "type": "Point", "coordinates": [ -1.6935641, 53.9044114 ] } }
]
}
