{
"type": "FeatureCollection",
"crs": { "type": "name", "properties": { "name": "urn:ogc:def:crs:OGC:1.3:CRS84" } },
"features": [
	{ "type": "Feature", "properties": { "osm_id": "301687728", "name": "Basilica", "other_tags": "\"building\"=>\"yes\",\"landuse\"=>\"mixed\"" }, "geometry": { "type": "Point", "coordinates": [ -1.5447464, 53.799113 ] } }
]
}
