{
"type": "FeatureCollection",
"crs": { "type": "name", "properties": { "name": "urn:ogc:def:crs:OGC:1.3:CRS84" } },
"features": [
	{ "type": "Feature", "properties": { "osm_id": "5981573977", "name": "The Nut Shop", "other_tags": "\"shop\"=>\"nuts\",\"fhrs:id\"=>\"319901\",\"addr:city\"=>\"Leeds\",\"addr:unit\"=>\"V\",\"addr:street\"=>\"Kirkgate\",\"addr:postcode\"=>\"LS2 7HH\",\"addr:housename\"=>\"Kirkgate Market\"" }, "geometry": { "type": "Point", "coordinates": [ -1.5399093, 53.7972486 ] } }
]
}
