{
"type": "FeatureCollection",
"crs": { "type": "name", "properties": { "name": "urn:ogc:def:crs:OGC:1.3:CRS84" } },
"features": [
	{ "type": "Feature", "properties": { "osm_id": "333799053", "name": "Jessops", "other_tags": "\"shop\"=>\"camera\",\"brand\"=>\"Jessops\",\"brand:wikidata\"=>\"Q3191701\",\"brand:wikipedia\"=>\"en:Jessops\"" }, "geometry": { "type": "Point", "coordinates": [ -1.54455, 53.7995741 ] } }
]
}
