{
"type": "FeatureCollection",
"crs": { "type": "name", "properties": { "name": "urn:ogc:def:crs:OGC:1.3:CRS84" } },
"features": [
	{ "type": "Feature", "properties": { "osm_id": "5981573979", "name": "Appliances Ltd", "other_tags": "\"shop\"=>\"appliance\",\"addr:city\"=>\"Leeds\",\"addr:unit\"=>\"Q\",\"addr:street\"=>\"Kirkgate\",\"addr:housename\"=>\"Kirkgate Market\"" }, "geometry": { "type": "Point", "coordinates": [ -1.5399238, 53.7970065 ] } },
	{ "type": "Feature", "properties": { "osm_id": "6022850284", "name": "Don Little", "other_tags": "\"shop\"=>\"appliance\"" }, "geometry": { "type": "Point", "coordinates": [ -1.537973, 53.7971771 ] } },
	{ "type": "Feature", "properties": { "osm_id": "7992740189", "name": "Appliance Depot UK", "other_tags": "\"shop\"=>\"appliance\"" }, "geometry": { "type": "Point", "coordinates": [ -1.3612816, 53.7265671 ] } }
]
}
