{
"type": "FeatureCollection",
"crs": { "type": "name", "properties": { "name": "urn:ogc:def:crs:OGC:1.3:CRS84" } },
"features": [
	{ "type": "Feature", "properties": { "osm_id": "5940387583", "name": "The Trophy Shop", "other_tags": "\"shop\"=>\"trophy\",\"website\"=>\"https:\/\/thetrophyshopleeds.co.uk\/\",\"addr:city\"=>\"Leeds\",\"addr:street\"=>\"Grand Arcade\",\"addr:postcode\"=>\"LS1 6PG\",\"addr:housenumber\"=>\"12\"" }, "geometry": { "type": "Point", "coordinates": [ -1.5406796, 53.8002327 ] } }
]
}
