{
"type": "FeatureCollection",
"crs": { "type": "name", "properties": { "name": "urn:ogc:def:crs:OGC:1.3:CRS84" } },
"features": [
	{ "type": "Feature", "properties": { "osm_id": "3191671066", "other_tags": "\"shop\"=>\"hats\"" }, "geometry": { "type": "Point", "coordinates": [ -1.7255919, 53.877486 ] } }
]
}
