{
"type": "FeatureCollection",
"crs": { "type": "name", "properties": { "name": "urn:ogc:def:crs:OGC:1.3:CRS84" } },
"features": [
	{ "type": "Feature", "properties": { "osm_id": "925707835", "amenity": "fuel", "other_tags": "\"brand\"=>\"Morrisons\",\"brand:wikidata\"=>\"Q922344\",\"contact:website\"=>\"https:\/\/my.morrisons.com\/storefinder\/1008\",\"fuel:diesel\"=>\"yes\",\"fuel:lpg\"=>\"yes\",\"fuel:octane_95\"=>\"yes\",\"operator\"=>\"Morrisons\",\"shop\"=>\"no\"" }, "geometry": { "type": "Point", "coordinates": [ -1.7107361, 53.8016854 ] } }
]
}
