{
"type": "FeatureCollection",
"crs": { "type": "name", "properties": { "name": "urn:ogc:def:crs:OGC:1.3:CRS84" } },
"features": [
	{ "type": "Feature", "properties": { "osm_id": "6600874645", "name": "Penningtons", "other_tags": "\"shop\"=>\"gun\",\"addr:town\"=>\"Castleford\",\"addr:street\"=>\"Bridge Street\",\"addr:postcode\"=>\"WF10 1HH\",\"addr:housenumber\"=>\"67\"" }, "geometry": { "type": "Point", "coordinates": [ -1.3480591, 53.7267272 ] } }
]
}
