{
"type": "FeatureCollection",
"crs": { "type": "name", "properties": { "name": "urn:ogc:def:crs:OGC:1.3:CRS84" } },
"features": [
	{ "type": "Feature", "properties": { "osm_id": "244449809", "amenity": "fountain" }, "geometry": { "type": "Point", "coordinates": [ -1.5488948, 53.8009261 ] } },
	{ "type": "Feature", "properties": { "osm_id": "247352921", "amenity": "fountain" }, "geometry": { "type": "Point", "coordinates": [ -1.5486361, 53.8010601 ] } },
	{ "type": "Feature", "properties": { "osm_id": "250196963", "amenity": "fountain", "other_tags": "\"image\"=>\"http:\/\/www.imagesofengland.org.uk\/Details\/Default.aspx?id=465359\",\"historic\"=>\"memorial\",\"description\"=>\"Inscription reads: ERECTED BY WILLIAM HENRY GOTT\/ OF ARMLEY HOUSE\/ IN COMMEMORATION OF THE SIXTIETH\/ YEAR OF THE REIGN OF HER MAJESTY\/ 1837. QUEEN VICTORIA. 1897.\"" }, "geometry": { "type": "Point", "coordinates": [ -1.5922254, 53.8000528 ] } },
	{ "type": "Feature", "properties": { "osm_id": "250341074", "amenity": "fountain" }, "geometry": { "type": "Point", "coordinates": [ -1.5438121, 53.7954766 ] } },
	{ "type": "Feature", "properties": { "osm_id": "274060297", "amenity": "fountain" }, "geometry": { "type": "Point", "coordinates": [ -1.5359301, 53.7985981 ] } },
	{ "type": "Feature", "properties": { "osm_id": "305686988", "amenity": "fountain", "other_tags": "\"drinking_water\"=>\"no\"" }, "geometry": { "type": "Point", "coordinates": [ -1.3377655, 53.7125016 ] } },
	{ "type": "Feature", "properties": { "osm_id": "305686990", "amenity": "fountain" }, "geometry": { "type": "Point", "coordinates": [ -1.3400347, 53.7123888 ] } },
	{ "type": "Feature", "properties": { "osm_id": "317593440", "amenity": "fountain", "other_tags": "\"drinkable\"=>\"no\"" }, "geometry": { "type": "Point", "coordinates": [ -1.7523689, 53.7924605 ] } },
	{ "type": "Feature", "properties": { "osm_id": "581453156", "amenity": "fountain" }, "geometry": { "type": "Point", "coordinates": [ -1.7831224, 53.648343 ] } },
	{ "type": "Feature", "properties": { "osm_id": "1003052661", "amenity": "fountain" }, "geometry": { "type": "Point", "coordinates": [ -1.4980354, 53.6834999 ] } },
	{ "type": "Feature", "properties": { "osm_id": "1241484268", "amenity": "fountain" }, "geometry": { "type": "Point", "coordinates": [ -1.7936694, 53.6486503 ] } },
	{ "type": "Feature", "properties": { "osm_id": "1283413817", "amenity": "fountain" }, "geometry": { "type": "Point", "coordinates": [ -1.9119418, 53.874666 ] } },
	{ "type": "Feature", "properties": { "osm_id": "1617873150", "amenity": "fountain" }, "geometry": { "type": "Point", "coordinates": [ -1.6745971, 53.7070609 ] } },
	{ "type": "Feature", "properties": { "osm_id": "1708475124", "amenity": "fountain" }, "geometry": { "type": "Point", "coordinates": [ -1.7930868, 53.5397851 ] } },
	{ "type": "Feature", "properties": { "osm_id": "2195805634", "name": "City Park", "amenity": "fountain" }, "geometry": { "type": "Point", "coordinates": [ -1.7546849, 53.7923542 ] } },
	{ "type": "Feature", "properties": { "osm_id": "2466453866", "amenity": "fountain", "other_tags": "\"drinking_water\"=>\"no\"" }, "geometry": { "type": "Point", "coordinates": [ -1.5053335, 53.8397029 ] } },
	{ "type": "Feature", "properties": { "osm_id": "2466453868", "amenity": "fountain", "other_tags": "\"drinking_water\"=>\"no\"" }, "geometry": { "type": "Point", "coordinates": [ -1.5051029, 53.8396459 ] } },
	{ "type": "Feature", "properties": { "osm_id": "2466453882", "amenity": "fountain", "other_tags": "\"drinking_water\"=>\"no\"" }, "geometry": { "type": "Point", "coordinates": [ -1.5056018, 53.8397693 ] } },
	{ "type": "Feature", "properties": { "osm_id": "2841809327", "amenity": "fountain" }, "geometry": { "type": "Point", "coordinates": [ -1.4971449, 53.8405609 ] } },
	{ "type": "Feature", "properties": { "osm_id": "4500820386", "amenity": "fountain" }, "geometry": { "type": "Point", "coordinates": [ -1.4599642, 53.7836472 ] } }
]
}
