{
"type": "FeatureCollection",
"crs": { "type": "name", "properties": { "name": "urn:ogc:def:crs:OGC:1.3:CRS84" } },
"features": [
	{ "type": "Feature", "properties": { "osm_id": "383880394", "name": "Dewsbury Household Waste and Recycling Site", "amenity": "waste_transfer_station", "other_tags": "\"url\"=>\"http:\/\/www.kirklees.gov.uk\/community\/localorgs\/azdetails.asp?OrgID=667\",\"recycling:oil\"=>\"yes\",\"recycling:soil\"=>\"yes\",\"recycling:glass\"=>\"yes\",\"recycling:paper\"=>\"yes\",\"recycling:rubble\"=>\"yes\",\"recycling:clothes\"=>\"yes\",\"recycling:batteries\"=>\"yes\",\"recycling:cardboard\"=>\"yes\",\"recycling:green_waste\"=>\"yes\",\"recycling:scrap_metal\"=>\"yes\",\"recycling:white_goods\"=>\"yes\"" }, "geometry": { "type": "Point", "coordinates": [ -1.6451159, 53.6818059 ] } }
]
}
