{
"type": "FeatureCollection",
"crs": { "type": "name", "properties": { "name": "urn:ogc:def:crs:OGC:1.3:CRS84" } },
"features": [
	{ "type": "Feature", "properties": { "osm_id": "9060122860", "other_tags": "\"description\"=>\"Fossilised tree trunk\",\"natural\"=>\"fossil\"" }, "geometry": { "type": "Point", "coordinates": [ -1.7201371, 53.8764562 ] } },
	{ "type": "Feature", "properties": { "osm_id": "11002715991", "name": "The Fossil Tree Stump", "other_tags": "\"description\"=>\"Fossilised tree stump and roots from the Carboniferous period, transported from Clayton and set in mortar\",\"geological:period\"=>\"Carboniferous\",\"mineral\"=>\"sandstone\",\"natural\"=>\"fossil\",\"taxon\"=>\"Stigmaria\"" }, "geometry": { "type": "Point", "coordinates": [ -1.775256, 53.8146533 ] } }
]
}
