{
"type": "FeatureCollection",
"crs": { "type": "name", "properties": { "name": "urn:ogc:def:crs:OGC:1.3:CRS84" } },
"features": [
	{ "type": "Feature", "properties": { "osm_id": "537113091", "name": "Blockbuster Video", "other_tags": "\"shop\"=>\"video\"" }, "geometry": { "type": "Point", "coordinates": [ -1.6913526, 53.6744219 ] } }
]
}
