{
"type": "FeatureCollection",
"crs": { "type": "name", "properties": { "name": "urn:ogc:def:crs:OGC:1.3:CRS84" } },
"features": [
	{ "type": "Feature", "properties": { "osm_id": "1011423096", "name": "Mirfield Auto Spares", "amenity": "scrapyard", "other_tags": "\"phone\"=>\"+44 1924 499104\",\"website\"=>\"mirfield-auto-spares.co.uk\"" }, "geometry": { "type": "Point", "coordinates": [ -1.6906672, 53.6724924 ] } }
]
}
