{
"type": "FeatureCollection",
"crs": { "type": "name", "properties": { "name": "urn:ogc:def:crs:OGC:1.3:CRS84" } },
"features": [
	{ "type": "Feature", "properties": { "osm_id": "1669158147", "name": "Hans & Tans", "other_tags": "\"shop\"=>\"beauty_salon\",\"phone\"=>\"+44 7515 774223\"" }, "geometry": { "type": "Point", "coordinates": [ -1.6738071, 53.7056483 ] } }
]
}
