{
"type": "FeatureCollection",
"crs": { "type": "name", "properties": { "name": "urn:ogc:def:crs:OGC:1.3:CRS84" } },
"features": [
	{ "type": "Feature", "properties": { "osm_id": "3451185036", "amenity": "notice_board" }, "geometry": { "type": "Point", "coordinates": [ -1.3516499, 53.7262975 ] } }
]
}
