{
"type": "FeatureCollection",
"crs": { "type": "name", "properties": { "name": "urn:ogc:def:crs:OGC:1.3:CRS84" } },
"features": [
	{ "type": "Feature", "properties": { "osm_id": "292321163", "name": "Croft House", "amenity": "residential_home", "other_tags": "\"fhrs:id\"=>\"283826\",\"addr:street\"=>\"High Street\",\"addr:postcode\"=>\"WF5 9RL\",\"addr:housenumber\"=>\"52a\"" }, "geometry": { "type": "Point", "coordinates": [ -1.586162, 53.6948277 ] } }
]
}
