{
"type": "FeatureCollection",
"crs": { "type": "name", "properties": { "name": "urn:ogc:def:crs:OGC:1.3:CRS84" } },
"features": [
	{ "type": "Feature", "properties": { "osm_id": "357751928", "name": "Stage Espresso & Brewbar;Veritas", "amenity": "fast_food;cafe;pub", "other_tags": "\"addr:city\"=>\"Leeds\",\"addr:housenumber\"=>\"41\",\"addr:postcode\"=>\"LS1 3BB\",\"addr:street\"=>\"Great George Street\",\"cuisine\"=>\"coffee_shop\",\"fhrs:id\"=>\"973645\",\"opening_hours\"=>\"Mo-Fr 08:00-17:00, Sa 09:00-17:00\",\"website\"=>\"www.stagecoffee.com\"" }, "geometry": { "type": "Point", "coordinates": [ -1.5509139, 53.800817 ] } }
]
}
