{
"type": "FeatureCollection",
"crs": { "type": "name", "properties": { "name": "urn:ogc:def:crs:OGC:1.3:CRS84" } },
"features": [
	{ "type": "Feature", "properties": { "osm_id": "8059792431", "name": "Zoot", "other_tags": "\"clothes\"=>\"men\",\"payment:cash\"=>\"yes\",\"payment:contactless\"=>\"yes\",\"payment:credit_cards\"=>\"yes\",\"payment:debit_cards\"=>\"yes\",\"shop\"=>\"clothes\"" }, "geometry": { "type": "Point", "coordinates": [ -1.3121298, 53.6914668 ] } }
]
}
