{
"type": "FeatureCollection",
"crs": { "type": "name", "properties": { "name": "urn:ogc:def:crs:OGC:1.3:CRS84" } },
"features": [
	{ "type": "Feature", "properties": { "osm_id": "317087645", "name": "Alea Casino", "amenity": "casino", "other_tags": "\"leisure\"=>\"casino\"" }, "geometry": { "type": "Point", "coordinates": [ -1.5317398, 53.7902359 ] } },
	{ "type": "Feature", "properties": { "osm_id": "3409737479", "name": "Casino Red", "amenity": "casino", "other_tags": "\"level\"=>\"1;2\"" }, "geometry": { "type": "Point", "coordinates": [ -1.7822489, 53.6487902 ] } }
]
}
