{
"type": "FeatureCollection",
"crs": { "type": "name", "properties": { "name": "urn:ogc:def:crs:OGC:1.3:CRS84" } },
"features": [
	{ "type": "Feature", "properties": { "osm_id": "6690648153", "name": "D T Wood", "other_tags": "\"shop\"=>\"wine;confectionery\"" }, "geometry": { "type": "Point", "coordinates": [ -1.4472958, 53.8123571 ] } }
]
}
