{
"type": "FeatureCollection",
"crs": { "type": "name", "properties": { "name": "urn:ogc:def:crs:OGC:1.3:CRS84" } },
"features": [
	{ "type": "Feature", "properties": { "osm_id": "967695816", "other_tags": "\"landuse\"=>\"allotments\"" }, "geometry": { "type": "Point", "coordinates": [ -1.7702427, 53.6464356 ] } },
	{ "type": "Feature", "properties": { "osm_id": "2090265569", "name": "Greenside Allotments", "other_tags": "\"landuse\"=>\"allotments\",\"source:name\"=>\"survey\"" }, "geometry": { "type": "Point", "coordinates": [ -1.7361485, 53.6422363 ] } }
]
}
