{
"type": "FeatureCollection",
"crs": { "type": "name", "properties": { "name": "urn:ogc:def:crs:OGC:1.3:CRS84" } },
"features": [
	{ "type": "Feature", "properties": { "osm_id": "1710584947", "other_tags": "\"landuse\"=>\"mineshaft\"" }, "geometry": { "type": "Point", "coordinates": [ -1.7843331, 53.5337765 ] } }
]
}
