{
"type": "FeatureCollection",
"crs": { "type": "name", "properties": { "name": "urn:ogc:def:crs:OGC:1.3:CRS84" } },
"features": [
	{ "type": "Feature", "properties": { "osm_id": "4353964291", "name": "Plastic Ivy", "other_tags": "\"addr:housenumber\"=>\"33\",\"addr:postcode\"=>\"WF12 7BB\",\"addr:street\"=>\"Leeds Road\",\"email\"=>\"staff@plasticivy.co.uk\",\"leisure\"=>\"sauna\",\"opening_hours\"=>\"We-Mo 12:00-22:00\",\"phone\"=>\"+44 1924 455600\",\"website\"=>\"https:\/\/www.plasticivy.co.uk\/\"" }, "geometry": { "type": "Point", "coordinates": [ -1.6242, 53.693535 ] } },
	{ "type": "Feature", "properties": { "osm_id": "4375827190", "name": "Base", "other_tags": "\"phone\"=>\"+44 113 242 7730\",\"leisure\"=>\"sauna\",\"website\"=>\"http:\/\/www.base-leeds.com\/#random\",\"addr:street\"=>\"Heaton's Court\",\"addr:postcode\"=>\"LS1 4LJ\",\"addr:housenumber\"=>\"7\"" }, "geometry": { "type": "Point", "coordinates": [ -1.5437251, 53.7949211 ] } },
	{ "type": "Feature", "properties": { "osm_id": "5463222466", "name": "Pound Tan", "other_tags": "\"leisure\"=>\"sauna\"" }, "geometry": { "type": "Point", "coordinates": [ -1.8596131, 53.7233499 ] } }
]
}
