{
"type": "FeatureCollection",
"crs": { "type": "name", "properties": { "name": "urn:ogc:def:crs:OGC:1.3:CRS84" } },
"features": [
	{ "type": "Feature", "properties": { "osm_id": "4579780115", "other_tags": "\"shop\"=>\"pie\"" }, "geometry": { "type": "Point", "coordinates": [ -2.012326, 53.7421878 ] } }
]
}
