{
"type": "FeatureCollection",
"crs": { "type": "name", "properties": { "name": "urn:ogc:def:crs:OGC:1.3:CRS84" } },
"features": [
	{ "type": "Feature", "properties": { "osm_id": "4866900366", "other_tags": "\"leisure\"=>\"picnic_table\"" }, "geometry": { "type": "Point", "coordinates": [ -1.9725542, 53.8239521 ] } }
]
}
