{
"type": "FeatureCollection",
"crs": { "type": "name", "properties": { "name": "urn:ogc:def:crs:OGC:1.3:CRS84" } },
"features": [
	{ "type": "Feature", "properties": { "osm_id": "2494911563", "name": "Donaldson Vets Sowerby Bridge", "amenity": "veterinary", "other_tags": "\"website\"=>\"http:\/\/www.donaldsonsvets.co.uk\/sowerby-bridge\/\",\"addr:city\"=>\"Sowerby Bridge\",\"addr:street\"=>\"Wakefield Road\",\"addr:country\"=>\"GB\",\"addr:postcode\"=>\"HX6 2AP\",\"addr:housenumber\"=>\"1\"" }, "geometry": { "type": "Point", "coordinates": [ -1.9012316, 53.7107719 ] } }
]
}
