{
"type": "FeatureCollection",
"crs": { "type": "name", "properties": { "name": "urn:ogc:def:crs:OGC:1.3:CRS84" } },
"features": [
	{ "type": "Feature", "properties": { "osm_id": "1420750902", "name": "Adventure-Spec", "other_tags": "\"shop\"=>\"motorcycle\",\"brand\"=>\"Motoz;AdvSpec;Klim;GoldenTyre;Lazer;Giant Loop;Kriega\",\"email\"=>\"info@adventure-spec.com\",\"phone\"=>\"+44 1422 882997\",\"website\"=>\"http:\/\/www.adventure-spec.com\",\"alt_name\"=>\"ADV Spec\",\"operator\"=>\"Adventure-Spec Ltd.\",\"addr:city\"=>\"Hebden Bridge\",\"addr:unit\"=>\"Unit 3\",\"addr:hamlet\"=>\"Mytholmroyd\",\"addr:street\"=>\"Cragg Road\",\"addr:country\"=>\"GB\",\"addr:postcode\"=>\"HX7 5EY\",\"opening_hours\"=>\"Mo-Fr 09:30-17:30; Su,PH off\",\"addr:housename\"=>\"Adventure-Spec\",\"motorcycle:parts\"=>\"yes;luggage\",\"motorcycle:tools\"=>\"sales\",\"motorcycle:clothes\"=>\"yes\"" }, "geometry": { "type": "Point", "coordinates": [ -1.9891093, 53.7255942 ] } }
]
}
