{
"type": "FeatureCollection",
"crs": { "type": "name", "properties": { "name": "urn:ogc:def:crs:OGC:1.3:CRS84" } },
"features": [
	{ "type": "Feature", "properties": { "osm_id": "262471195", "amenity": "water_point", "other_tags": "\"waterway\"=>\"water_point\"" }, "geometry": { "type": "Point", "coordinates": [ -2.0975968, 53.7124264 ] } }
]
}
