{
"type": "FeatureCollection",
"crs": { "type": "name", "properties": { "name": "urn:ogc:def:crs:OGC:1.3:CRS84" } },
"features": [
	{ "type": "Feature", "properties": { "osm_id": "6835693138", "other_tags": "\"leisure\"=>\"picnic_table\"" }, "geometry": { "type": "Point", "coordinates": [ -2.0183891, 53.7588176 ] } }
]
}
