{
"type": "FeatureCollection",
"crs": { "type": "name", "properties": { "name": "urn:ogc:def:crs:OGC:1.3:CRS84" } },
"features": [
	{ "type": "Feature", "properties": { "osm_id": "3722746330", "name": "Optcare", "other_tags": "\"addr:street\"=>\"Navigation Close\",\"shop\"=>\"medical_supply\",\"toilets:wheelchair\"=>\"yes\",\"wheelchair\"=>\"yes\",\"wheelchair:description\"=>\"NHS Wheelchair Service\"" }, "geometry": { "type": "Point", "coordinates": [ -1.8287516, 53.6936716 ] } },
	{ "type": "Feature", "properties": { "osm_id": "5572259408", "name": "Tongji Chinese Medicine", "other_tags": "\"image\"=>\"https:\/\/www.geograph.org.uk\/photo\/1590442\",\"shop\"=>\"medical_supply\",\"website\"=>\"https:\/\/www.westgatearcade.co.uk\/tongji-chinese-medicine\"" }, "geometry": { "type": "Point", "coordinates": [ -1.8585429, 53.7214438 ] } }
]
}
