{
"type": "FeatureCollection",
"crs": { "type": "name", "properties": { "name": "urn:ogc:def:crs:OGC:1.3:CRS84" } },
"features": [
	{ "type": "Feature", "properties": { "osm_id": "5569969824", "name": "Better Lives at 42", "amenity": "social_facility", "other_tags": "\"addr:city\"=>\"Halifax\",\"addr:street\"=>\"Market Street\",\"addr:country\"=>\"GB\",\"social_facility\"=>\"outreach\",\"addr:housenumber\"=>\"42\"" }, "geometry": { "type": "Point", "coordinates": [ -1.8587735, 53.7221374 ] } }
]
}
