{
"type": "FeatureCollection",
"crs": { "type": "name", "properties": { "name": "urn:ogc:def:crs:OGC:1.3:CRS84" } },
"features": [
	{ "type": "Feature", "properties": { "osm_id": "5371260044", "amenity": "compressed_air" }, "geometry": { "type": "Point", "coordinates": [ -1.8351929, 53.6886965 ] } },
	{ "type": "Feature", "properties": { "osm_id": "8385200743", "amenity": "compressed_air", "other_tags": "\"lit\"=>\"yes\"" }, "geometry": { "type": "Point", "coordinates": [ -1.853582, 53.7025097 ] } },
	{ "type": "Feature", "properties": { "osm_id": "8396758207", "amenity": "compressed_air" }, "geometry": { "type": "Point", "coordinates": [ -1.859762, 53.7181997 ] } },
	{ "type": "Feature", "properties": { "osm_id": "8408011712", "amenity": "compressed_air" }, "geometry": { "type": "Point", "coordinates": [ -1.8552017, 53.7266058 ] } },
	{ "type": "Feature", "properties": { "osm_id": "8454989234", "amenity": "compressed_air" }, "geometry": { "type": "Point", "coordinates": [ -1.8929391, 53.7496961 ] } }
]
}
