{
"type": "FeatureCollection",
"crs": { "type": "name", "properties": { "name": "urn:ogc:def:crs:OGC:1.3:CRS84" } },
"features": [
	{ "type": "Feature", "properties": { "osm_id": "5452280961", "name": "CEX", "other_tags": "\"shop\"=>\"pawnbroker\"" }, "geometry": { "type": "Point", "coordinates": [ -1.8574995, 53.7232229 ] } }
]
}
