{
"type": "FeatureCollection",
"crs": { "type": "name", "properties": { "name": "urn:ogc:def:crs:OGC:1.3:CRS84" } },
"features": [
	{ "type": "Feature", "properties": { "osm_id": "374406326", "amenity": "car_wash", "other_tags": "\"operator\"=>\"arc\"" }, "geometry": { "type": "Point", "coordinates": [ -1.7787717, 53.7162403 ] } },
	{ "type": "Feature", "properties": { "osm_id": "3294487843", "amenity": "car_wash" }, "geometry": { "type": "Point", "coordinates": [ -1.9860589, 53.7325381 ] } }
]
}
