{
"type": "FeatureCollection",
"crs": { "type": "name", "properties": { "name": "urn:ogc:def:crs:OGC:1.3:CRS84" } },
"features": [
	{ "type": "Feature", "properties": { "osm_id": "1627266134", "amenity": "vending_machine", "other_tags": "\"vending\"=>\"parking_tickets\"" }, "geometry": { "type": "Point", "coordinates": [ -1.7797593, 53.7001263 ] } }
]
}
