{
"type": "FeatureCollection",
"crs": { "type": "name", "properties": { "name": "urn:ogc:def:crs:OGC:1.3:CRS84" } },
"features": [
	{ "type": "Feature", "properties": { "osm_id": "6878645650", "other_tags": "\"natural\"=>\"wetland\",\"salt\"=>\"no\",\"tidal\"=>\"no\",\"wetland\"=>\"bog\"" }, "geometry": { "type": "Point", "coordinates": [ -1.9283949, 53.7182568 ] } }
]
}
