{
"type": "FeatureCollection",
"crs": { "type": "name", "properties": { "name": "urn:ogc:def:crs:OGC:1.3:CRS84" } },
"features": [
	{ "type": "Feature", "properties": { "osm_id": "1026886565", "name": "Pound Store", "other_tags": "\"shop\"=>\"variety_store\"" }, "geometry": { "type": "Point", "coordinates": [ -1.7811683, 53.7015562 ] } }
]
}
