{
"type": "FeatureCollection",
"crs": { "type": "name", "properties": { "name": "urn:ogc:def:crs:OGC:1.3:CRS84" } },
"features": [
	{ "type": "Feature", "properties": { "osm_id": "8222543346", "amenity": "vending_machine", "other_tags": "\"vending\"=>\"public_transport_tickets\"" }, "geometry": { "type": "Point", "coordinates": [ -2.1045582, 53.6964373 ] } },
	{ "type": "Feature", "properties": { "osm_id": "8663459431", "amenity": "vending_machine", "other_tags": "\"vending\"=>\"public_transport_tickets\"" }, "geometry": { "type": "Point", "coordinates": [ -2.0087729, 53.7376627 ] } },
	{ "type": "Feature", "properties": { "osm_id": "8805455598", "amenity": "vending_machine", "other_tags": "\"vending\"=>\"public_transport_tickets\"" }, "geometry": { "type": "Point", "coordinates": [ -1.9813982, 53.7290749 ] } },
	{ "type": "Feature", "properties": { "osm_id": "9139440340", "amenity": "vending_machine", "other_tags": "\"currency:GBP\"=>\"yes\",\"operator\"=>\"Calderdale Council\",\"vending\"=>\"parking_tickets\"" }, "geometry": { "type": "Point", "coordinates": [ -1.7822065, 53.7001234 ] } },
	{ "type": "Feature", "properties": { "osm_id": "9139440341", "amenity": "vending_machine", "other_tags": "\"currency:GBP\"=>\"yes\",\"operator\"=>\"Calderdale Council\",\"vending\"=>\"parking_tickets\"" }, "geometry": { "type": "Point", "coordinates": [ -1.7828926, 53.6999947 ] } },
	{ "type": "Feature", "properties": { "osm_id": "9525220838", "amenity": "vending_machine", "other_tags": "\"currency:GBP\"=>\"yes\",\"operator\"=>\"Calderdale Council\",\"payment:app\"=>\"yes\",\"payment:cash\"=>\"yes\",\"vending\"=>\"parking_tickets\"" }, "geometry": { "type": "Point", "coordinates": [ -1.7839387, 53.7022357 ] } }
]
}
