{
"type": "FeatureCollection",
"crs": { "type": "name", "properties": { "name": "urn:ogc:def:crs:OGC:1.3:CRS84" } },
"features": [
	{ "type": "Feature", "properties": { "osm_id": "4579780115", "name": "Country Stores", "other_tags": "\"shop\"=>\"deli\",\"addr:city\"=>\"Hebden Bridge\",\"addr:street\"=>\"Saint George's Square\",\"addr:postcode\"=>\"HX7 8ET\",\"addr:housenumber\"=>\"11-13\"" }, "geometry": { "type": "Point", "coordinates": [ -2.012326, 53.7421878 ] } },
	{ "type": "Feature", "properties": { "osm_id": "6174845398", "name": "Leaf", "other_tags": "\"shop\"=>\"deli\",\"fhrs:id\"=>\"1106428\",\"addr:city\"=>\"Halifax\",\"addr:unit\"=>\"RE2\",\"diet:vegan\"=>\"only\",\"addr:street\"=>\"The Piece Hall\",\"source:addr\"=>\"FHRS Open Data\",\"addr:country\"=>\"GB\",\"addr:postcode\"=>\"HX1 1RE\",\"opening_hours\"=>\"Mo-Sa 10:00-18:00; Su 11:00-16:00\",\"diet:vegetarian\"=>\"only\"" }, "geometry": { "type": "Point", "coordinates": [ -1.8565903, 53.7223222 ] } },
	{ "type": "Feature", "properties": { "osm_id": "7164960456", "name": "Brian's", "other_tags": "\"shop\"=>\"deli\"" }, "geometry": { "type": "Point", "coordinates": [ -2.0962952, 53.7147434 ] } },
	{ "type": "Feature", "properties": { "osm_id": "7164960457", "name": "Ham Corner", "other_tags": "\"shop\"=>\"deli\"" }, "geometry": { "type": "Point", "coordinates": [ -2.0961893, 53.7147609 ] } }
]
}
