{
"type": "FeatureCollection",
"crs": { "type": "name", "properties": { "name": "urn:ogc:def:crs:OGC:1.3:CRS84" } },
"features": [
	{ "type": "Feature", "properties": { "osm_id": "4579780115", "name": "Country Stores", "other_tags": "\"addr:city\"=>\"Hebden Bridge\",\"addr:housenumber\"=>\"11-13\",\"addr:postcode\"=>\"HX7 8ET\",\"addr:street\"=>\"Saint George's Square\",\"shop\"=>\"deli\"" }, "geometry": { "type": "Point", "coordinates": [ -2.012326, 53.7421878 ] } }
]
}
