{
"type": "FeatureCollection",
"crs": { "type": "name", "properties": { "name": "urn:ogc:def:crs:OGC:1.3:CRS84" } },
"features": [
	{ "type": "Feature", "properties": { "osm_id": "5463222471", "name": "Janet Greens", "other_tags": "\"shop\"=>\"photo\"" }, "geometry": { "type": "Point", "coordinates": [ -1.8597257, 53.7233404 ] } },
	{ "type": "Feature", "properties": { "osm_id": "5569969829", "name": "Max Spielman", "other_tags": "\"shop\"=>\"photo\"" }, "geometry": { "type": "Point", "coordinates": [ -1.8590176, 53.7226278 ] } }
]
}
