{
"type": "FeatureCollection",
"crs": { "type": "name", "properties": { "name": "urn:ogc:def:crs:OGC:1.3:CRS84" } },
"features": [
	{ "type": "Feature", "properties": { "osm_id": "5371260044", "amenity": "compressed_air" }, "geometry": { "type": "Point", "coordinates": [ -1.835146, 53.6888037 ] } }
]
}
