{
"type": "FeatureCollection",
"crs": { "type": "name", "properties": { "name": "urn:ogc:def:crs:OGC:1.3:CRS84" } },
"features": [
	{ "type": "Feature", "properties": { "osm_id": "1026886565", "name": "Pound Store", "other_tags": "\"shop\"=>\"variety_store\"" }, "geometry": { "type": "Point", "coordinates": [ -1.7811683, 53.7015562 ] } },
	{ "type": "Feature", "properties": { "osm_id": "5502173699", "name": "Poundland", "other_tags": "\"shop\"=>\"variety_store\",\"fhrs:id\"=>\"347289\",\"addr:city\"=>\"Halifax\",\"addr:street\"=>\"Market Street\",\"source:addr\"=>\"FHRS Open Data\",\"addr:country\"=>\"GB\",\"addr:postcode\"=>\"HX1 1PB\",\"addr:housename\"=>\"Westgate House\",\"addr:housenumber\"=>\"17-21\"" }, "geometry": { "type": "Point", "coordinates": [ -1.8586313, 53.7226262 ] } },
	{ "type": "Feature", "properties": { "osm_id": "5579351376", "name": "Poundland", "other_tags": "\"shop\"=>\"variety_store\",\"fhrs:id\"=>\"347938\",\"addr:city\"=>\"Halifax\",\"addr:street\"=>\"Market Street\",\"source:addr\"=>\"FHRS Open Data\",\"addr:country\"=>\"GB\",\"addr:postcode\"=>\"HX1 1PD\",\"addr:housename\"=>\"Westgate House\",\"addr:housenumber\"=>\"43-45\"" }, "geometry": { "type": "Point", "coordinates": [ -1.8582505, 53.7218597 ] } }
]
}
