{
"type": "FeatureCollection",
"crs": { "type": "name", "properties": { "name": "urn:ogc:def:crs:OGC:1.3:CRS84" } },
"features": [
	{ "type": "Feature", "properties": { "osm_id": "538416256", "name": "Rex Cinema", "amenity": "cinema", "other_tags": "\"addr:city\"=>\"Elland\",\"addr:postcode\"=>\"HX5 0DF\",\"addr:street\"=>\"Coronation Street\",\"fhrs:id\"=>\"347198\",\"source:addr\"=>\"FHRS Open Data\",\"toilets:wheelchair\"=>\"no\",\"wheelchair\"=>\"limited\"" }, "geometry": { "type": "Point", "coordinates": [ -1.8378945, 53.6851413 ] } }
]
}
