{
"type": "FeatureCollection",
"crs": { "type": "name", "properties": { "name": "urn:ogc:def:crs:OGC:1.3:CRS84" } },
"features": [
	{ "type": "Feature", "properties": { "osm_id": "3722746330", "name": "Optcare", "other_tags": "\"shop\"=>\"medical_supply\",\"wheelchair\"=>\"yes\",\"addr:street\"=>\"Navigation Close\",\"toilets:wheelchair\"=>\"yes\",\"wheelchair:description\"=>\"NHS Wheelchair Service\"" }, "geometry": { "type": "Point", "coordinates": [ -1.8287516, 53.6936716 ] } }
]
}
